{
  "updated_at": "2026-05-26T14:55:24.425965+09:00",
  "channels": [
    {
      "name": "스마트스토어",
      "url": "https://sell.smartstore.naver.com",
      "status": "ok",
      "error": null,
      "updated_at": "2026-05-26T14:52:35.267366+09:00",
      "summary": {
        "orders_new": 0,
        "inquiries_unanswered": 0,
        "reviews_unanswered": 0,
        "qna_unanswered": 0,
        "inquiry_unanswered": 0,
        "talktalk_unanswered": 0
      },
      "orders": [],
      "inquiries": [],
      "reviews": []
    },
    {
      "name": "카카오",
      "url": "https://shopping-sell.kakao.com/hub",
      "status": "ok",
      "error": null,
      "updated_at": "2026-05-26T14:52:57.265440+09:00",
      "summary": {
        "orders_new": 0,
        "inquiries_unanswered": 0,
        "reviews_unanswered": 0,
        "pluschat_unanswered": 0
      },
      "orders": [],
      "inquiries": [],
      "reviews": []
    },
    {
      "name": "G마켓(ESM+)",
      "url": "https://www.esmplus.com/Home",
      "status": "ok",
      "error": null,
      "updated_at": "2026-05-26T14:53:08.889282+09:00",
      "summary": {
        "orders_new": 0,
        "inquiries_unanswered": 0,
        "reviews_unanswered": 0
      },
      "orders": [],
      "inquiries": [],
      "reviews": []
    },
    {
      "name": "11번가",
      "url": "http://soffice.11st.co.kr/view/main",
      "status": "ok",
      "error": null,
      "updated_at": "2026-05-26T14:53:35.933514+09:00",
      "summary": {
        "orders_new": 0,
        "inquiries_unanswered": 0,
        "reviews_unanswered": 0
      },
      "orders": [],
      "inquiries": [],
      "reviews": []
    },
    {
      "name": "토스쇼핑",
      "url": "https://shopping-seller.toss.im/home",
      "status": "ok",
      "error": null,
      "updated_at": "2026-05-26T14:53:55.915734+09:00",
      "summary": {
        "orders_new": 0,
        "inquiries_unanswered": 0,
        "reviews_unanswered": 0
      },
      "orders": [],
      "inquiries": [],
      "reviews": []
    },
    {
      "name": "와디즈",
      "url": "https://www.wadiz.kr/web/main",
      "status": "ok",
      "error": null,
      "updated_at": "2026-05-26T14:54:17.616536+09:00",
      "summary": {
        "orders_new": 6,
        "inquiries_unanswered": 6,
        "reviews_unanswered": 6
      },
      "orders": [],
      "inquiries": [],
      "reviews": []
    },
    {
      "name": "알리익스프레스",
      "url": "https://sell.aliexpress.com",
      "status": "ok",
      "error": null,
      "updated_at": "2026-05-26T14:54:43.982952+09:00",
      "summary": {
        "orders_new": 0,
        "inquiries_unanswered": 0,
        "reviews_unanswered": 0
      },
      "orders": [],
      "inquiries": [],
      "reviews": []
    },
    {
      "name": "오아이스",
      "url": "https://www.oasis.co.kr:9886/order/seller/list",
      "status": "error",
      "error": "ElementHandle.fill: Timeout 30000ms exceeded.\nCall log:\n    - fill(\"2026-05-26\")\n  - attempting fill action\n    2 × waiting for element to be visible, enabled and editable\n      - element is not editable\n    - retrying fill action\n    - waiting 20ms\n    2 × waiting for element to be visible, enabled and editable\n      - element is not editable\n    - retrying fill action\n      - waiting 100ms\n    60 × waiting for element to be visible, enabled and editable\n       - element is not editable\n     - retrying fill action\n       - waiting 500ms\n",
      "updated_at": "2026-05-26T14:55:24.376701+09:00",
      "summary": {
        "orders_new": 0,
        "inquiries_unanswered": 0,
        "reviews_unanswered": 0
      },
      "orders": [],
      "inquiries": [],
      "reviews": []
    }
  ]
}